hasItChanged
