Metadata-Version: 1.1
Name: hasItChanged
Version: 0.0.4
Summary: Monitor websites for changes
Home-page: https://github.com/growdaisy/hasItChanged
Author: Pokey Rule
Author-email: pokey@growdaisy.com
License: MIT
Keywords: email smtp sendgrid http
Platform: UNKNOWN
Classifier: Development Status :: 3 - Alpha
Classifier: Intended Audience :: Developers
Classifier: Topic :: Communications :: Email
Classifier: License :: OSI Approved :: MIT License
Classifier: Programming Language :: Python :: 2
Classifier: Programming Language :: Python :: 2.6
Classifier: Programming Language :: Python :: 2.7
Classifier: Programming Language :: Python :: 3
Classifier: Programming Language :: Python :: 3.2
Classifier: Programming Language :: Python :: 3.3
Classifier: Programming Language :: Python :: 3.4
